ziggostatus/__init__.py
ziggostatus-0.1.1.dist-info/LICENSE
ziggostatus-0.1.1.dist-info/LICENSE.md
ziggostatus-0.1.1.dist-info/METADATA
ziggostatus-0.1.1.dist-info/WHEEL
ziggostatus-0.1.1.dist-info/top_level.txt
ziggostatus-0.1.1.dist-info/RECORD
