Metadata-Version: 2.1
Name: ziggostatus
Version: 0.1.1
Summary: Asynchronous Python client for getting Ziggo outages & announcements.
Home-page: https://github.com/DevSecNinja/ZiggoStatus
Author: Jean-Paul van Ravensberg
Author-email: 14926452+DevSecNinja@users.noreply.github.com
License: MIT license
Keywords: ziggo,status,outages,announcements,api,async,client
Platform: UNKNOWN
Classifier: Framework :: AsyncIO
Classifier: Intended Audience :: Developers
Classifier: License :: OSI Approved :: MIT License
Classifier: Natural Language :: English
Classifier: Programming Language :: Python :: 3.7
Classifier: Programming Language :: Python :: 3.8
Classifier: Programming Language :: Python :: 3
Classifier: Topic :: Software Development :: Libraries :: Python Modules
Requires-Dist: aiohttp (>=3.0.0)
